[{"pk": 1, "model": "products.category", "fields": {"name": "relationships", "friendly_name": "Relationships"}}, {"pk": 2, "model": "products.category", "fields": {"name": "awareness", "friendly_name": "Awareness development"}}, {"pk": 3, "model": "products.category", "fields": {"name": "mental_health", "friendly_name": "Mental health"}}, {"pk": 4, "model": "products.category", "fields": {"name": "sport", "friendly_name": "Sport"}}, {"pk": 5, "model": "products.category", "fields": {"name": "creating_cv", "friendly_name": "Creating CV"}}, {"pk": 6, "model": "products.category", "fields": {"name": "personal_letter", "friendly_name": "Personal letter"}}]